dblp_webxml_parser/__init__.py
dblp_webxml_parser/person.py
dblp_webxml_parser/record.py
dblp_webxml_parser/venue.py
dblp_webxml_parser-0.1.0.dist-info/licenses/LICENSE
dblp_webxml_parser-0.1.0.dist-info/METADATA
dblp_webxml_parser-0.1.0.dist-info/WHEEL
dblp_webxml_parser-0.1.0.dist-info/top_level.txt
dblp_webxml_parser-0.1.0.dist-info/RECORD
