Metadata-Version: 2.4
Name: dblp-webxml-parser
Version: 0.1.0
Summary: A lightweight parser for DBLP website XML pages (record, person, venue pages), not the database dump.
Author-email: yindaheng98 <yindaheng98@gmail.com>
License: MIT
Project-URL: Homepage, https://github.com/yindaheng98/dblp-webxml-parser
Keywords: dblp,parser,xml,academic,bibliography,publication,web-scraping
Classifier: Development Status :: 4 - Beta
Classifier: Intended Audience :: Developers
Classifier: Intended Audience :: Science/Research
Classifier: Programming Language :: Python :: 3
Classifier: Programming Language :: Python :: 3.10
Classifier: Programming Language :: Python :: 3.11
Classifier: Programming Language :: Python :: 3.12
Classifier: Programming Language :: Python :: 3.13
Classifier: License :: OSI Approved :: MIT License
Classifier: Operating System :: OS Independent
Classifier: Topic :: Scientific/Engineering
Classifier: Topic :: Text Processing :: Markup :: XML
Requires-Python: >=3.10
License-File: LICENSE
Provides-Extra: dev
Requires-Dist: pytest>=7.0.0; extra == "dev"
Requires-Dist: pytest-asyncio>=0.21.0; extra == "dev"
Requires-Dist: aiohttp>=3.8.0; extra == "dev"
Dynamic: license-file
